{
  "kind": "collectionType",
  "collectionName": "transactions",
  "info": {
    "singularName": "transaction",
    "pluralName": "transactions",
    "displayName": "Transaction",
    "description": ""
  },
  "options": {
    "draftAndPublish": true
  },
  "pluginOptions": {},
  "attributes": {
    "type": {
      "type": "enumeration",
      "enum": [
        "income",
        "expense"
      ]
    },
    "amount": {
      "type": "decimal"
    },
    "category": {
      "type": "string"
    },
    "memo": {
      "type": "text"
    },
    "date": {
      "type": "date"
    },
    "users_permissions_user": {
      "type": "relation",
      "relation": "manyToOne",
      "target": "plugin::users-permissions.user",
      "inversedBy": "transactions"
    }
  }
}
